{
  "whiteboard": {
    "title": "Courses",
    "subtitle": "Intermediate",
    "descriptions": [
      {
        {"icon": "page",
        "description": "Lesson 17"
      },
      {
        "description": "Flipped classroom"
      },
      {
        "description": "What can we do? (Cycle 1)"
      }
    ]
  },
  "contents": [
    {
      "paragraphs": [
        {
          "paragraph": [
            {
              "boldText": "Under construction..."
            }
          ]
        }
      ]
    }
  ]
}
