{
  "whiteboard": {
    "title": "Extra",
    "subtitle": "Grammar",
    "descriptions": [
      {
        "description": "Elementary"
      },
      {
        "description": "Unit 68"
      },
      {
        "description": "a cake / some cake / some cakes (countable/uncoutable 2)"
      }
    ]
  },
  "contents": [
    {
      "paragraphs": [
        {
          "paragraph": [
            {
              "boldText": "Under construction..."
            }
          ]
        }
      ]
    }
  ]
}
