{
  "whiteboard": {
    "title": "Courses",
    "descriptions": [
      { "icon": "book",
        "description": "Beginner"
      },
      {
        "icon": "page",
        "description": "Lesson 7"
      },
      {
        "icon": "presentation",
        "description": "Classwork • Where are you from? (Cycle 1)"
      },
      {
        "description": ""
      }
    ]
  },
  "contents": [
    {
      "paragraphs": [
        {
          "paragraph": [
            {
              "boldText": "Under construction..."
            }
          ]
        }
      ]
    }
  ]
}
