{
  "whiteboard": {
    "title": "Extras",
    "subtitle": "Audiobooks"
  },
  "contents": [
    {
      "ribbon": {
        "icon": "books",
        "label": "Starter (Pre-A1) 200 headwords"
      },
      "card": {
        "bgColor": "var(--gray-3)",
        "icon": "kid",
        "label": "Kids",
        "items": [
          {
            "svg": "book",
            "link": "/extras/audiobooks/starter/kids/cinderella/page",
            "label": "Cinderella"
          },
          {
            "svg": "book",
            "link": "/extras/audiobooks/starter/kids/dumbo/page",
            "label": "Dumbo"
          },
          {
            "svg": "book",
            "link": "/extras/audiobooks/starter/kids/finding- nemo/page",
            "label": "Finding Nemo"
          },
          {
            "svg": "book",
            "link": "/extras/audiobooks/starter/kids/puss-in-boots/page",
            "label": "Puss-in-Boots"
          },
          {
            "svg": "book",
            "link": "/extras/audiobooks/starter/kids/sleeping-beauty/page",
            "label": "Sleeping Beauty"
          }
        ]
      }
    },
    {
      "card": {
        "bgColor": "var(--gray-3)",
        "icon": "adult",
        "label": "Young learners / Adults",
        "items": [
          {
            "svg": "book",
            "link": "/extras/audiobooks/starter/young-learners-adults/a-new-zealand-adventure/page",
            "label": "A New Zealand Adventure"
          },
          {
            "svg": "book",
            "link": "/extras/audiobooks/starter/young-learners-adults/flying-home/page",
            "label": "Flying home"
          },
          {
            "svg": "book",
            "link": "/extras/audiobooks/starter/young-learners-adults/marcel-and-the-mona-lisa/page",
            "label": "Marcel and the Mona Lisa"
          },
          {
            "svg": "book",
            "link": "/extras/audiobooks/starter/young-learners-adults/marcel-and-the-white-star/page",
            "label": "Marcel and the White Star"
          },
          {
            "svg": "book",
            "link": "/extras/audiobooks/starter/young-learners-adults/newspaper-chase/page",
            "label": "Newspaper Chase"
          },
          {
            "svg": "book",
            "link": "/extras/audiobooks/starter/young-learners-adults/simon-and-the-spy/page",
            "label": "Simon and the Spy"
          },
          {
            "svg": "book",
            "link": "/extras/audiobooks/starter/young-learners-adults/the-fireboy/page",
            "label": "The Fireboy"
          },
          {
            "svg": "book",
            "link": "/extras/audiobooks/starter/young-learners-adults/the-last-photo/page",
            "label": "The Last Photo"
          },
          {
            "svg": "book",
            "link": "/extras/audiobooks/starter/young-learners-adults/the-leopard-and-the-lighthouse/page",
            "label": "The Leopard and the Lighthouse"
          },
          {
            "svg": "book",
            "link": "/extras/audiobooks/starter/young-learners-adults/the-pearl-jam/page",
            "label": "The Pearl Girl"
          },
          {
            "svg": "book",
            "link": "/extras/audiobooks/starter/young-learners-adults/the-troy-stone/page",
            "label": "The Troy Stone"
          },
          {
            "svg": "book",
            "link": "/extras/audiobooks/starter/young-learners-adults/the-white-oryx/page",
            "label": "The White Oryx"
          },
          {
            "svg": "book",
            "link": "/extras/audiobooks/starter/young-learners-adults/who-wants-to-be-a-star/page",
            "label": "Who Wants to be a star"
          }
        ]
      }
    },
    {
      "ribbon": {
        "icon": "books",
        "label": "Beginner (A1)"
      }
    },
    {
      "card": {
        "bgColor": "var(--gray-3)",
        "icon": "kid",
        "label": "Kids",
        "items": [
          {
            "svg": "book",
            "link": "/extras/audiobooks/starter/kids/",
            "label": "..."
          }
        ]
      }
    },
    {
      "card": {
        "bgColor": "var(--gray-3)",
        "icon": "adult",
        "label": "Young learners / Adults",
        "items": [
          {
            "svg": "book",
            "link": "/extras/audiobooks/beginner/young-learners-adults/sherlock-holmes/page",
            "label": "Sherlock Holmes"
          }
        ]
      }
    },
    {
      "ribbon": {
        "icon": "books",
        "label": "Elementary (A2)"
      }
    },
    {
      "card": {
        "bgColor": "var(--gray-3)",
        "icon": "kid",
        "label": "Kids",
        "items": [
          {
            "svg": "book",
            "link": "/extras/audiobooks/starter/kids/",
            "label": "..."
          }
        ]
      }
    },
    {
      "card": {
        "bgColor": "var(--gray-3)",
        "icon": "adult",
        "label": "Young learners / Adults",
        "items": [
          {
            "svg": "book",
            "link": "/extras/audiobooks/starter/young-learners-adults/",
            "label": "..."
          }
        ]
      }
    },
    {
      "ribbon": {
        "icon": "books",
        "label": "Pre-Intermediate (A2-B1)"
      }
    },
    {
      "card": {
        "bgColor": "var(--gray-3)",
        "icon": "kid",
        "label": "Kids",
        "items": [
          {
            "svg": "book",
            "link": "/extras/audiobooks/starter/kids/",
            "label": "..."
          }
        ]
      }
    },
    {
      "card": {
        "bgColor": "var(--gray-3)",
        "icon": "adult",
        "label": "Young learners / Adults",
        "items": [
          {
            "svg": "book",
            "link": "/extras/audiobooks/starter/young-learners-adults/",
            "label": "..."
          }
        ]
      }
    },
    {
      "ribbon": {
        "icon": "books",
        "label": "Intermediate (B1)"
      }
    },
    {
      "card": {
        "bgColor": "var(--gray-3)",
        "icon": "kid",
        "label": "Kids",
        "items": [
          {
            "svg": "book",
            "link": "/extras/audiobooks/starter/kids/",
            "label": "..."
          }
        ]
      }
    },
    {
      "card": {
        "bgColor": "var(--gray-3)",
        "icon": "adult",
        "label": "Young learners / Adults",
        "items": [
          {
            "svg": "book",
            "link": "/extras/audiobooks/starter/young-learners-adults/",
            "label": "..."
          }
        ]
      }
    }
  ]
}
